PyDicomGrouping/__init__.py
PyDicomGrouping/main.py
PyDicomGrouping/utils.py
PyDicomGrouping/dicom_standard_scrapping/DicomStandardEnums.py
PyDicomGrouping/dicom_standard_scrapping/__init__.py
PyDicomGrouping/dicom_standard_scrapping/webscraping.py
PyDicomGrouping/dicom_standard_scrapping/DicomStandardTreeNodeCaches/12-LeadECG.pkl
PyDicomGrouping/dicom_standard_scrapping/DicomStandardTreeNodeCaches/AcquisitionContextSR.pkl
PyDicomGrouping/dicom_standard_scrapping/DicomStandardTreeNodeCaches/AdvancedBlendingPresentationState.pkl
PyDicomGrouping/dicom_standard_scrapping/DicomStandardTreeNodeCaches/AmbulatoryECG.pkl
PyDicomGrouping/dicom_standard_scrapping/DicomStandardTreeNodeCaches/ArterialPulseWaveform.pkl
PyDicomGrouping/dicom_standard_scrapping/DicomStandardTreeNodeCaches/AutorefractionMeasurements.pkl
PyDicomGrouping/dicom_standard_scrapping/DicomStandardTreeNodeCaches/BasicCardiacElectrophysiologyWaveform.pkl
PyDicomGrouping/dicom_standard_scrapping/DicomStandardTreeNodeCaches/BasicDirectory.pkl
PyDicomGrouping/dicom_standard_scrapping/DicomStandardTreeNodeCaches/BasicStructuredDisplay.pkl
PyDicomGrouping/dicom_standard_scrapping/DicomStandardTreeNodeCaches/BasicTextSR.pkl
PyDicomGrouping/dicom_standard_scrapping/DicomStandardTreeNodeCaches/BasicVoiceAudioWaveform.pkl
PyDicomGrouping/dicom_standard_scrapping/DicomStandardTreeNodeCaches/BlendingSoftcopyPresentationState.pkl
PyDicomGrouping/dicom_standard_scrapping/DicomStandardTreeNodeCaches/BodyPositionWaveform.pkl
PyDicomGrouping/dicom_standard_scrapping/DicomStandardTreeNodeCaches/BreastProjectionX-RayImage.pkl
PyDicomGrouping/dicom_standard_scrapping/DicomStandardTreeNodeCaches/BreastTomosynthesisImage.pkl
PyDicomGrouping/dicom_standard_scrapping/DicomStandardTreeNodeCaches/C-ArmPhoton-ElectronRadiation.pkl
PyDicomGrouping/dicom_standard_scrapping/DicomStandardTreeNodeCaches/C-ArmPhoton-ElectronRadiationRecord.pkl
PyDicomGrouping-0.1.13.dist-info/METADATA
PyDicomGrouping-0.1.13.dist-info/WHEEL
PyDicomGrouping-0.1.13.dist-info/top_level.txt
PyDicomGrouping-0.1.13.dist-info/RECORD
